infercnv_mcp/__init__.py
infercnv_mcp/cli.py
infercnv_mcp/schema/__init__.py
infercnv_mcp/schema/preset/pl.py
infercnv_mcp/schema/preset/tl.py
infercnv_mcp/schema/preset/util.py
infercnv_mcp/server/__init__.py
infercnv_mcp/server/preset/pl.py
infercnv_mcp/server/preset/pp.py
infercnv_mcp/server/preset/tl.py
infercnv_mcp/server/preset/util.py
infercnv_mcp-0.2.0.dist-info/METADATA
infercnv_mcp-0.2.0.dist-info/WHEEL
infercnv_mcp-0.2.0.dist-info/entry_points.txt
infercnv_mcp-0.2.0.dist-info/RECORD
