Metadata-Version: 2.4
Name: infercnv-mcp
Version: 0.2.0
Summary: Natural language interface for CNV inference from scRNA-Seq data with infercnvpy through MCP.
Project-URL: Homepage, http://scmcphub.org/
Project-URL: Repository, https://github.com/scmcphub/infercnv-mcp
Project-URL: Documentation, https://docs.scmcphub.org/
Author-email: shuang <hsh-me@outlook.com>, mugpeng <yc47680@um.edu.mo>
Keywords: AI,CNV,agent,bioinformatics,llm,mcp,model context protocol,scRNA-seq,single cell
Requires-Python: >=3.10
Requires-Dist: fastmcp>=2.4
Requires-Dist: infercnvpy
Requires-Dist: nest-asyncio
Requires-Dist: scanpy
Requires-Dist: scmcp-shared>=0.5.0
